fileghost/__init__.py
fileghost/fileghost.py
fileghost-0.1.4.dist-info/LICENSE
fileghost-0.1.4.dist-info/METADATA
fileghost-0.1.4.dist-info/WHEEL
fileghost-0.1.4.dist-info/top_level.txt
fileghost-0.1.4.dist-info/RECORD
