Metadata-Version: 2.1
Name: fileghost
Version: 0.1.4
Summary: Open-source file encryption
Home-page: https://github.com/0ut0flin3/fileghost
Author: 0ut0flin3
Author-email: 0ut0flin3 <0ut0flin3@protonmail.com>
License: MIT License
Project-URL: Homepage, https://github.com/0ut0flin3/fileghost
Keywords: encryption,file,opensource
Classifier: License :: OSI Approved :: MIT License
Classifier: Programming Language :: Python
Classifier: Programming Language :: Python :: 3
Requires-Python: >=3.6
License-File: LICENSE
